{
  "breadcrumbs.enabled": false,
  "editor.bracketPairColorization.enabled": true,
  "editor.defaultFormatter": "esbenp.prettier-vscode",
  "editor.formatOnSave": true,
  "editor.minimap.enabled": false,
  "editor.tabSize": 2,
  "emmet.includeLanguages": {
    "javascript": "javascriptreact",
    "liquid": "html"
  },
  "explorer.confirmDelete": false,
  "explorer.confirmDragAndDrop": false,
  "files.autoSave": "off",
  "javascript.updateImportsOnFileMove.enabled": "always",
  "security.workspace.trust.untrustedFiles": "open",
  "telemetry.telemetryLevel": "off",
  "typescript.updateImportsOnFileMove.enabled": "always",
  "workbench.iconTheme": "material-icon-theme",
  "workbench.sideBar.location": "right",
  "workbench.startupEditor": "none",
  "window.zoomLevel": 1
}
